o2_google_spreadsheet.py
omatify_google_spreadsheet.py
o2_google_spreadsheet-0.4.dist-info/METADATA
o2_google_spreadsheet-0.4.dist-info/WHEEL
o2_google_spreadsheet-0.4.dist-info/top_level.txt
o2_google_spreadsheet-0.4.dist-info/RECORD
