Metadata-Version: 2.1
Name: o2-google-spreadsheet
Version: 0.4
Summary: Google Spreadsheet helper file
Home-page: https://github.com/hudgeon
Author: Hudge
Author-email: doug@mybusinessautomated.com
License: UNKNOWN
Platform: UNKNOWN
Classifier: Programming Language :: Python :: 3
Classifier: License :: OSI Approved :: MIT License
Classifier: Operating System :: OS Independent
Requires-Dist: requests
Requires-Dist: pandas
Requires-Dist: gspread
Requires-Dist: oauth2client
Requires-Dist: money2float
